   {
				"Codigo": "HT001",
                "Nombre": "Sheraton",
                "CodigoDeCiudad": "MIA",
                "Calificacion": 5,
                "Direccion": 
				
				{
					"Calle": "Collins Ave",
					"Numero": 1234,
					"CP": 7000,
					"Latitud": 25.845362706221916,
					"Longitud": -80.11993195337358,
					
				}	
                "Disponibilidad": 
				
				{
					"Nombre": "Intermedio",
					"TarifaHab": 50000, 
					"Capacidad": 4,
					"Adultos": 2,
					"Menores": 2, 
					"Infantes": 0,
					
				}
                
				"HabitacionFechaDis":
				
				{
					"FechaHab": "29-06-2023",
					"CantHab": 3
					
				}
            
				
				
	},
	
	
	
	 {
				"Codigo": "HT002",
                "Nombre": "Four Seasons",
                "CodigoDeCiudad": "MAD",
                "Calificacion": 5,
                "Direccion": 
				
				{
					"Calle": "C. de Sevilla",
					"Numero": 30,
					"CP": 28014,
					"Latitud": 40.41707269127456,
					"Longitud": -3.7004233112454163,
					
				}	
                "Disponibilidad": 
				
				{
					"Nombre": "Deluxe",
					"TarifaHab": 75200, 
					"Capacidad": 5,
					"Adultos": 3,
					"Menores": 2, 
					"Infantes": 0,
					
				}
                
				"HabitacionFechaDis":
				
				{
					"FechaHab": "29-06-2023",
					"CantHab": 3
					
				}
            
				
				
	},
	 
	
	{
				"Codigo": "HT003",
                "Nombre": "ibis budget Meudon",
                "CodigoDeCiudad": "PAR",
                "Calificacion": 3,
                "Direccion": 
				
				{
					"Calle": "Bis Rue de Paris",
					"Numero": 3,
					"CP": 92190,
					"Latitud": 48.81806260303906,
					"Longitud": 2.2493296544913317,
					
				}	
                "Disponibilidad": 
				
				{
					"Nombre": "Standard",
					"TarifaHab": 16927, 
					"Capacidad": 3,
					"Adultos": 2,
					"Menores": 1, 
					"Infantes": 0,
					
				}
                
				"HabitacionFechaDis":
				
				{
					"FechaHab": "18-06-2023",
					"CantHab": 3
					
				}
            
				
				
	},
	
	 
	
	{
				"Codigo": "HT004",
                "Nombre": "Hotel Imperial",
                "CodigoDeCiudad": "TOK",
                "Calificacion": 4,
                "Direccion": 
				
				{
					"Calle": "Uchisaiwaicho",
					"Numero": 3,
					"CP": 10085,
					"Latitud": 35.67291568730059,
					"Longitud": 139.75805021595886,
					
				}	
                "Disponibilidad": 
				
				{
					"Nombre": "Standard",
					"TarifaHab": 67189, 
					"Capacidad": 2,
					"Adultos": 2,
					"Menores": 0, 
					"Infantes": 0,
					
				}
                
				"HabitacionFechaDis":
				
				{
					"FechaHab": "21-06-2023",
					"CantHab": 4
					
				}
            
				
				
	},
	
	
		{
				"Codigo": "HT005",
                "Nombre": "Fendi Private Suites",
                "CodigoDeCiudad": "PAR",
                "Calificacion": 3,
                "Direccion": 
				
				{
					"Calle": "Villa della Fontanella",
					"Numero": 48,
					"CP": 100095,
					"Latitud": 41.90511675430925,
					"Longitud":  12.496799466785122,
					
				}	
                "Disponibilidad": 
				
				{
					"Nombre": "Duplex",
					"TarifaHab": 135000, 
					"Capacidad": 4,
					"Adultos": 2,
					"Menores": 2, 
					"Infantes": 0,
					
				}
                
				"HabitacionFechaDis":
				
				{
					"FechaHab": "15-06-2023",
					"CantHab": 5
					
				}
            
				
				
	},
	
	 
	   {
				"Codigo": "HT006",
                "Nombre": "Sofitel",
                "CodigoDeCiudad": "BUE",
                "Calificacion": 5,
                "Direccion": 
				
				{
					"Calle": "Posadas ",
					"Numero": 1232,
					"CP": 1001,
					"Latitud": -34.589276818961046,,
					"Longitud": -58.38411528860917,
					
				}	
                "Disponibilidad": 
				
				{
					"Nombre": "Deluxe",
					"TarifaHab": 88900, 
					"Capacidad": 4,
					"Adultos": 2,
					"Menores": 2, 
					"Infantes": 0,
					
				}
                
				"HabitacionFechaDis":
				
				{
					"FechaHab": "22-06-2023",
					"CantHab": 3
					
				}
            
				
				
	},